qrucible/__init__.py
qrucible/qrucible.abi3.so
qrucible-1.0.0.dist-info/METADATA
qrucible-1.0.0.dist-info/WHEEL
qrucible-1.0.0.dist-info/entry_points.txt
qrucible-1.0.0.dist-info/licenses/LICENSE
qrucible-1.0.0.dist-info/RECORD
