Metadata-Version: 2.4
Name: qrucible
Version: 1.0.0
Classifier: Development Status :: 5 - Production/Stable
Classifier: Intended Audience :: Developers
Classifier: Intended Audience :: Financial and Insurance Industry
Classifier: Topic :: Office/Business :: Financial :: Investment
Classifier: Topic :: Scientific/Engineering :: Information Analysis
Classifier: Programming Language :: Rust
Classifier: Programming Language :: Python :: 3
Classifier: Programming Language :: Python :: 3.10
Classifier: Programming Language :: Python :: 3.11
Classifier: Programming Language :: Python :: 3.12
Classifier: Programming Language :: Python :: 3.13
Classifier: Programming Language :: Python :: Implementation :: CPython
Classifier: Operating System :: OS Independent
Classifier: License :: OSI Approved :: Apache Software License
Requires-Dist: numpy>=1.24
Requires-Dist: pytest>=7.4 ; extra == 'dev'
Requires-Dist: maturin>=1.4,<2.0 ; extra == 'dev'
Requires-Dist: pandas>=2.0 ; extra == 'dev'
Requires-Dist: mkdocs>=1.5 ; extra == 'docs'
Requires-Dist: mkdocs-material>=9.5 ; extra == 'docs'
Requires-Dist: mkdocs-section-index>=0.3 ; extra == 'docs'
Requires-Dist: pandas>=2.0 ; extra == 'easy'
Provides-Extra: dev
Provides-Extra: docs
Provides-Extra: easy
License-File: LICENSE
Summary: Qrucible: hybrid stateful backtesting engine with Rust hot path
Keywords: backtesting,trading,finance,quantitative,rust,python
Author: Qrucible Contributors
Maintainer: Charles Freidenreich
License: Apache-2.0
Requires-Python: >=3.10
Project-URL: Documentation, https://charlesfreidenreich.github.io/Qrucible/
Project-URL: Homepage, https://github.com/charlesfreidenreich/Qrucible
Project-URL: Issues, https://github.com/charlesfreidenreich/Qrucible/issues
Project-URL: Repository, https://github.com/charlesfreidenreich/Qrucible
